[[0.152242,{"lines":{"0":[["                                                                                                                     ",{}]],"1":[["                                                                                                                     ",{}]],"2":[["                                                                                                                     ",{}]],"3":[["                                                                                                                     ",{}]],"4":[["                                                                                                                     ",{}]],"5":[["                                                                                                                     ",{}]],"6":[["                                                                                                                     ",{}]],"7":[["                                                                                                                     ",{}]],"8":[["                                                                                                                     ",{}]],"9":[["                                                                                                                     ",{}]],"10":[["                                                                                                                     ",{}]],"11":[["                                                                                                                     ",{}]],"12":[["                                                                                                                     ",{}]],"13":[["                                                                                                                     ",{}]],"14":[["                                                                                                                     ",{}]],"15":[["                                                                                                                     ",{}]],"16":[["                                                                                                                     ",{}]]},"cursor":{"x":0,"y":0,"visible":true}}],[0.017534,{"lines":{"0":[["➜ ",{"fg":1,"bold":true}],[" ",{"fg":2,"bold":true}],["plines ",{"fg":6,"bold":true}],["git:(",{"fg":4,"bold":true}],["rspec-3-upgrade",{"fg":1,"bold":true}],[") ",{"fg":4,"bold":true}],["                                                                                     ",{}]]},"cursor":{"x":32}}],[0.391434,{"lines":{"0":[["➜ ",{"fg":1,"bold":true}],[" ",{"fg":2,"bold":true}],["plines ",{"fg":6,"bold":true}],["git:(",{"fg":4,"bold":true}],["rspec-3-upgrade",{"fg":1,"bold":true}],[") ",{"fg":4,"bold":true}],["v                                                                                    ",{}]]},"cursor":{"x":33}}],[0.1114,{"lines":{"0":[["➜ ",{"fg":1,"bold":true}],[" ",{"fg":2,"bold":true}],["plines ",{"fg":6,"bold":true}],["git:(",{"fg":4,"bold":true}],["rspec-3-upgrade",{"fg":1,"bold":true}],[") ",{"fg":4,"bold":true}],["vi                                                                                   ",{}]]},"cursor":{"x":34}}],[0.06365899999999999,{"lines":{"0":[["➜ ",{"fg":1,"bold":true}],[" ",{"fg":2,"bold":true}],["plines ",{"fg":6,"bold":true}],["git:(",{"fg":4,"bold":true}],["rspec-3-upgrade",{"fg":1,"bold":true}],[") ",{"fg":4,"bold":true}],["vim                                                                                  ",{}]]},"cursor":{"x":35}}],[0.056113,{"cursor":{"x":36}}],[0.167767,{"lines":{"0":[["➜ ",{"fg":1,"bold":true}],[" ",{"fg":2,"bold":true}],["plines ",{"fg":6,"bold":true}],["git:(",{"fg":4,"bold":true}],["rspec-3-upgrade",{"fg":1,"bold":true}],[") ",{"fg":4,"bold":true}],["vim G                                                                                ",{}]]},"cursor":{"x":37}}],[0.064027,{"lines":{"0":[["➜ ",{"fg":1,"bold":true}],[" ",{"fg":2,"bold":true}],["plines ",{"fg":6,"bold":true}],["git:(",{"fg":4,"bold":true}],["rspec-3-upgrade",{"fg":1,"bold":true}],[") ",{"fg":4,"bold":true}],["vim Ge                                                                               ",{}]]},"cursor":{"x":38}}],[0.152584,{"lines":{"0":[["➜ ",{"fg":1,"bold":true}],[" ",{"fg":2,"bold":true}],["plines ",{"fg":6,"bold":true}],["git:(",{"fg":4,"bold":true}],["rspec-3-upgrade",{"fg":1,"bold":true}],[") ",{"fg":4,"bold":true}],["vim Gem                                                                              ",{}]]},"cursor":{"x":39}}],[0.157389,{"lines":{"0":[["➜ ",{"fg":1,"bold":true}],[" ",{"fg":2,"bold":true}],["plines ",{"fg":6,"bold":true}],["git:(",{"fg":4,"bold":true}],["rspec-3-upgrade",{"fg":1,"bold":true}],[") ",{"fg":4,"bold":true}],["vim Gemfile                                                                          ",{}]]},"cursor":{"x":43}}],[0.313811,{"cursor":{"x":0,"y":1}}],[0.001045,{}],[0.44384,{"lines":{"0":[["                                                                                                                     ",{}]],"1":[["▽                                                                                                                    ",{}]]},"cursor":{"y":0}}],[0.001318,{"lines":{"0":[["                                                                                                                     ",{"fg":253}]],"1":[["                                                                                                                     ",{"fg":253}]],"2":[["                                                                                                                     ",{"fg":253}]],"3":[["                                                                                                                     ",{"fg":253}]],"4":[["                                                                                                                     ",{"fg":253}]],"5":[["                                                                                                                     ",{"fg":253}]],"6":[["                                                                                                                     ",{"fg":253}]],"7":[["                                                                                                                     ",{"fg":253}]],"8":[["                                                                                                                     ",{"fg":253}]],"9":[["                                                                                                                     ",{"fg":253}]],"10":[["                                                                                                                     ",{"fg":253}]],"11":[["                                                                                                                     ",{"fg":253}]],"12":[["                                                                                                                     ",{"fg":253}]],"13":[["                                                                                                                     ",{"fg":253}]],"14":[["                                                                                                                     ",{"fg":253}]],"15":[["                                                                                                                     ",{"fg":253}]],"16":[["\"Gemfile\" 8L, 172C                                                                                                   ",{"fg":253}]]},"cursor":{"x":18,"y":16,"visible":false}}],[0.08333699999999999,{}],[0.004971000000000001,{"lines":{"0":[["  1 ",{"fg":15,"bg":232}],["source ",{"fg":253}],["'https://rubygems.org'",{"fg":82}],["¬",{"fg":8}],["                                                                                   ",{"fg":253}]],"1":[["  2 ",{"fg":15,"bg":232}],["¬",{"fg":8}],["                                                                                                                ",{"fg":253}]],"2":[["  3 ",{"fg":15,"bg":232}],["# Specify your gem's dependencies in plines.gemspec",{"fg":92}],["¬",{"fg":8}],["                                                             ",{"fg":253}]],"3":[["  4 ",{"fg":15,"bg":232}],["gemspec",{"fg":253}],["¬",{"fg":8}],["                                                                                                         ",{"fg":253}]],"4":[["  5 ",{"fg":15,"bg":232}],["¬",{"fg":8}],["                                                                                                                ",{"fg":253}]],"5":[["  6 ",{"fg":15,"bg":232}],["gem ",{"fg":253}],["'qless'",{"fg":82}],[", ",{"fg":253}],["git",{"fg":30}],[": ",{"fg":253}],["'git://github.com/seomoz/qless.git'",{"fg":82}],["¬",{"fg":8}],["                                                           ",{"fg":253}]],"6":[["  7 ",{"fg":15,"bg":232}],["¬",{"fg":8}],["                                                                                                                ",{"fg":253}]],"7":[["  8 ",{"fg":15,"bg":232}],["gem ",{"fg":253}],["'rspec'",{"fg":82}],[", ",{"fg":253}],["'~> 2.99.0'",{"fg":82}],["¬",{"fg":8}],["                                                                                        ",{"fg":253}]],"8":[["~                                                                                                                    ",{"fg":8}]],"9":[["~                                                                                                                    ",{"fg":8}]],"10":[["~                                                                                                                    ",{"fg":8}]],"11":[["~                                                                                                                    ",{"fg":8}]],"12":[["~                                                                                                                    ",{"fg":8}]],"13":[["~                                                                                                                    ",{"fg":8}]],"14":[["~                                                                                                                    ",{"fg":8}]],"15":[["Gemfile  Line:8/8[100%]Col:21Buf:#1[57][0x39]                                                                        ",{"fg":0,"bg":15,"bold":true}]]},"cursor":{"x":24,"y":7,"visible":true}}],[0.9213440000000001,{"lines":{"15":[["Gemfile  Line:8/8[100%]Col:20Buf:#1[57][0x39]                                                                        ",{"fg":0,"bg":15,"bold":true}]]},"cursor":{"x":23}}],[0.2241,{"lines":{"15":[["Gemfile  Line:8/8[100%]Col:19Buf:#1[46][0x2E]                                                                        ",{"fg":0,"bg":15,"bold":true}]]},"cursor":{"x":22}}],[0.143697,{"lines":{"15":[["Gemfile  Line:8/8[100%]Col:18Buf:#1[50][0x32]                                                                        ",{"fg":0,"bg":15,"bold":true}]]},"cursor":{"x":21}}],[0.5117969999999999,{"lines":{"16":[["-- INSERT --",{"fg":253,"bold":true}],["                                                                                                         ",{"fg":253}]]},"cursor":{"x":12,"y":16,"visible":false}}],[0.000654,{"lines":{"7":[["  8 ",{"fg":15,"bg":232}],["gem ",{"fg":253}],["'rspec'",{"fg":82}],[", ",{"fg":253}],["'~> '",{"fg":82}],["¬",{"fg":8}],["                                                                                              ",{"fg":253}]],"15":[["Gemfile [+] Line:8/8[100%]Col:18Buf:#1[39][0x27]                                                                     ",{"fg":0,"bg":15,"bold":true}]]},"cursor":{"x":21,"y":7,"visible":true}}],[0.239659,{"lines":{"7":[["  8 ",{"fg":15,"bg":232}],["gem ",{"fg":253}],["'rspec'",{"fg":82}],[", ",{"fg":253}],["'~> 3'",{"fg":82}],["¬",{"fg":8}],["                                                                                             ",{"fg":253}]],"15":[["Gemfile [+] Line:8/8[100%]Col:19Buf:#1[39][0x27]                                                                     ",{"fg":0,"bg":15,"bold":true}]]},"cursor":{"x":22}}],[0.130909,{"lines":{"7":[["  8 ",{"fg":15,"bg":232}],["gem ",{"fg":253}],["'rspec'",{"fg":82}],[", ",{"fg":253}],["'~> 3.'",{"fg":82}],["¬",{"fg":8}],["                                                                                            ",{"fg":253}]],"15":[["Gemfile [+] Line:8/8[100%]Col:20Buf:#1[39][0x27]                                                                     ",{"fg":0,"bg":15,"bold":true}]]},"cursor":{"x":23}}],[0.253468,{"lines":{"7":[["  8 ",{"fg":15,"bg":232}],["gem ",{"fg":253}],["'rspec'",{"fg":82}],[", ",{"fg":253}],["'~> 3.0'",{"fg":82}],["¬",{"fg":8}],["                                                                                           ",{"fg":253}]],"15":[["Gemfile [+] Line:8/8[100%]Col:21Buf:#1[39][0x27]                                                                     ",{"fg":0,"bg":15,"bold":true}]]},"cursor":{"x":24}}],[0.408903,{"lines":{"16":[["                                                                                                                     ",{"fg":253}]]},"cursor":{"x":23}}],[0.430167,{"cursor":{"visible":false}}],[0.000418,{"lines":{"15":[["Gemfile [+] Line:8/8[100%]Col:20Buf:#1[48][0x30]                                                                     ",{"fg":0,"bg":15,"bold":true}]],"16":[[":                                                                                                                    ",{"fg":253}]]},"cursor":{"x":1,"y":16,"visible":true}}],[0.063747,{"lines":{"16":[[":w                                                                                                                   ",{"fg":253}]]},"cursor":{"x":2}}],[0.111878,{"cursor":{"x":0}}],[0.002227,{"lines":{"16":[["\"Gemfile\" 8L, 169C written                                                                                           ",{"fg":253}]]},"cursor":{"x":26,"visible":false}}],[0.06779200000000001,{"lines":{"15":[["Gemfile  Line:8/8[100%]Col:20Buf:#1[48][0x30]                                                                        ",{"fg":0,"bg":15,"bold":true}]]},"cursor":{"x":23,"y":7,"visible":true}}],[0.249764,{"lines":{"16":[[":                                                                                                                    ",{"fg":253}]]},"cursor":{"x":1,"y":16}}],[0.135939,{"lines":{"16":[[":q                                                                                                                   ",{"fg":253}]]},"cursor":{"x":2}}],[0.224101,{"lines":{"16":[[":qa                                                                                                                  ",{"fg":253}]]},"cursor":{"x":3}}],[0.288019,{"cursor":{"x":0}}],[0.004813,{"lines":{"0":[["➜ ",{"fg":1,"bold":true}],[" ",{"fg":2,"bold":true}],["plines ",{"fg":6,"bold":true}],["git:(",{"fg":4,"bold":true}],["rspec-3-upgrade",{"fg":1,"bold":true}],[") ",{"fg":4,"bold":true}],["vim Gemfile                                                                          ",{}]],"1":[["                                                                                                                     ",{}]],"2":[["                                                                                                                     ",{}]],"3":[["                                                                                                                     ",{}]],"4":[["                                                                                                                     ",{}]],"5":[["                                                                                                                     ",{}]],"6":[["                                                                                                                     ",{}]],"7":[["                                                                                                                     ",{}]],"8":[["                                                                                                                     ",{}]],"9":[["                                                                                                                     ",{}]],"10":[["                                                                                                                     ",{}]],"11":[["                                                                                                                     ",{}]],"12":[["                                                                                                                     ",{}]],"13":[["                                                                                                                     ",{}]],"14":[["                                                                                                                     ",{}]],"15":[["                                                                                                                     ",{}]],"16":[["                                                                                                                     ",{}]]},"cursor":{"y":1}}],[0.013464,{"lines":{"1":[["➜ ",{"fg":1,"bold":true}],[" ",{"fg":2,"bold":true}],["plines ",{"fg":6,"bold":true}],["git:(",{"fg":4,"bold":true}],["rspec-3-upgrade",{"fg":1,"bold":true}],[") ",{"fg":4,"bold":true}],["✗",{"fg":3,"bold":true}],[" ",{"fg":4,"bold":true}],["                                                                                   ",{}]]},"cursor":{"x":34}}],[0.325881,{"lines":{"1":[["➜ ",{"fg":1,"bold":true}],[" ",{"fg":2,"bold":true}],["plines ",{"fg":6,"bold":true}],["git:(",{"fg":4,"bold":true}],["rspec-3-upgrade",{"fg":1,"bold":true}],[") ",{"fg":4,"bold":true}],["✗",{"fg":3,"bold":true}],[" ",{"fg":4,"bold":true}],["b                                                                                  ",{}]]},"cursor":{"x":35}}],[0.103712,{"lines":{"1":[["➜ ",{"fg":1,"bold":true}],[" ",{"fg":2,"bold":true}],["plines ",{"fg":6,"bold":true}],["git:(",{"fg":4,"bold":true}],["rspec-3-upgrade",{"fg":1,"bold":true}],[") ",{"fg":4,"bold":true}],["✗",{"fg":3,"bold":true}],[" ",{"fg":4,"bold":true}],["bu                                                                                 ",{}]]},"cursor":{"x":36}}],[0.12001,{"lines":{"1":[["➜ ",{"fg":1,"bold":true}],[" ",{"fg":2,"bold":true}],["plines ",{"fg":6,"bold":true}],["git:(",{"fg":4,"bold":true}],["rspec-3-upgrade",{"fg":1,"bold":true}],[") ",{"fg":4,"bold":true}],["✗",{"fg":3,"bold":true}],[" ",{"fg":4,"bold":true}],["bun                                                                                ",{}]]},"cursor":{"x":37}}],[0.064022,{"lines":{"1":[["➜ ",{"fg":1,"bold":true}],[" ",{"fg":2,"bold":true}],["plines ",{"fg":6,"bold":true}],["git:(",{"fg":4,"bold":true}],["rspec-3-upgrade",{"fg":1,"bold":true}],[") ",{"fg":4,"bold":true}],["✗",{"fg":3,"bold":true}],[" ",{"fg":4,"bold":true}],["bund                                                                               ",{}]]},"cursor":{"x":38}}],[0.071868,{"lines":{"1":[["➜ ",{"fg":1,"bold":true}],[" ",{"fg":2,"bold":true}],["plines ",{"fg":6,"bold":true}],["git:(",{"fg":4,"bold":true}],["rspec-3-upgrade",{"fg":1,"bold":true}],[") ",{"fg":4,"bold":true}],["✗",{"fg":3,"bold":true}],[" ",{"fg":4,"bold":true}],["bundl                                                                              ",{}]]},"cursor":{"x":39}}],[0.064262,{"lines":{"1":[["➜ ",{"fg":1,"bold":true}],[" ",{"fg":2,"bold":true}],["plines ",{"fg":6,"bold":true}],["git:(",{"fg":4,"bold":true}],["rspec-3-upgrade",{"fg":1,"bold":true}],[") ",{"fg":4,"bold":true}],["✗",{"fg":3,"bold":true}],[" ",{"fg":4,"bold":true}],["bundle                                                                             ",{}]]},"cursor":{"x":40}}],[0.073896,{"cursor":{"x":41}}],[0.117939,{"lines":{"1":[["➜ ",{"fg":1,"bold":true}],[" ",{"fg":2,"bold":true}],["plines ",{"fg":6,"bold":true}],["git:(",{"fg":4,"bold":true}],["rspec-3-upgrade",{"fg":1,"bold":true}],[") ",{"fg":4,"bold":true}],["✗",{"fg":3,"bold":true}],[" ",{"fg":4,"bold":true}],["bundle i                                                                           ",{}]]},"cursor":{"x":42}}],[0.031995,{"lines":{"1":[["➜ ",{"fg":1,"bold":true}],[" ",{"fg":2,"bold":true}],["plines ",{"fg":6,"bold":true}],["git:(",{"fg":4,"bold":true}],["rspec-3-upgrade",{"fg":1,"bold":true}],[") ",{"fg":4,"bold":true}],["✗",{"fg":3,"bold":true}],[" ",{"fg":4,"bold":true}],["bundle in                                                                          ",{}]]},"cursor":{"x":43}}],[0.047979,{"lines":{"1":[["➜ ",{"fg":1,"bold":true}],[" ",{"fg":2,"bold":true}],["plines ",{"fg":6,"bold":true}],["git:(",{"fg":4,"bold":true}],["rspec-3-upgrade",{"fg":1,"bold":true}],[") ",{"fg":4,"bold":true}],["✗",{"fg":3,"bold":true}],[" ",{"fg":4,"bold":true}],["bundle ins                                                                         ",{}]]},"cursor":{"x":44}}],[0.056199,{"lines":{"1":[["➜ ",{"fg":1,"bold":true}],[" ",{"fg":2,"bold":true}],["plines ",{"fg":6,"bold":true}],["git:(",{"fg":4,"bold":true}],["rspec-3-upgrade",{"fg":1,"bold":true}],[") ",{"fg":4,"bold":true}],["✗",{"fg":3,"bold":true}],[" ",{"fg":4,"bold":true}],["bundle inst                                                                        ",{}]]},"cursor":{"x":45}}],[0.087654,{"lines":{"1":[["➜ ",{"fg":1,"bold":true}],[" ",{"fg":2,"bold":true}],["plines ",{"fg":6,"bold":true}],["git:(",{"fg":4,"bold":true}],["rspec-3-upgrade",{"fg":1,"bold":true}],[") ",{"fg":4,"bold":true}],["✗",{"fg":3,"bold":true}],[" ",{"fg":4,"bold":true}],["bundle insta                                                                       ",{}]]},"cursor":{"x":46}}],[0.096196,{"lines":{"1":[["➜ ",{"fg":1,"bold":true}],[" ",{"fg":2,"bold":true}],["plines ",{"fg":6,"bold":true}],["git:(",{"fg":4,"bold":true}],["rspec-3-upgrade",{"fg":1,"bold":true}],[") ",{"fg":4,"bold":true}],["✗",{"fg":3,"bold":true}],[" ",{"fg":4,"bold":true}],["bundle instal                                                                      ",{}]]},"cursor":{"x":47}}],[0.127659,{"lines":{"1":[["➜ ",{"fg":1,"bold":true}],[" ",{"fg":2,"bold":true}],["plines ",{"fg":6,"bold":true}],["git:(",{"fg":4,"bold":true}],["rspec-3-upgrade",{"fg":1,"bold":true}],[") ",{"fg":4,"bold":true}],["✗",{"fg":3,"bold":true}],[" ",{"fg":4,"bold":true}],["bundle install                                                                     ",{}]]},"cursor":{"x":48}}],[0.168002,{"cursor":{"x":0,"y":2}}],[0.001142,{}],[0.820128,{"lines":{"2":[["Fetching gem metadata from https://rubygems.org/                                                                     ",{}]]},"cursor":{"x":48}}],[0.001104,{"lines":{"2":[["Fetching gem metadata from https://rubygems.org/.                                                                    ",{}]]},"cursor":{"x":49}}],[0.541996,{"lines":{"2":[["Fetching gem metadata from https://rubygems.org/..                                                                   ",{}]]},"cursor":{"x":50}}],[1.012424,{"lines":{"2":[["Fetching gem metadata from https://rubygems.org/...                                                                  ",{}]]},"cursor":{"x":51}}],[0.542494,{"lines":{"2":[["Fetching gem metadata from https://rubygems.org/....                                                                 ",{}]]},"cursor":{"x":52}}],[0.142956,{"lines":{"2":[["Fetching gem metadata from https://rubygems.org/.....                                                                ",{}]]},"cursor":{"x":53}}],[0.176977,{"lines":{"2":[["Fetching gem metadata from https://rubygems.org/......                                                               ",{}]]},"cursor":{"x":54}}],[0.106846,{"lines":{"2":[["Fetching gem metadata from https://rubygems.org/.......                                                              ",{}]]},"cursor":{"x":55}}],[1.557867,{"cursor":{"x":0,"y":3}}],[0.081724,{"lines":{"3":[["Fetching additional metadata from https://rubygems.org/.                                                             ",{}]]},"cursor":{"x":56}}],[0.228576,{"lines":{"3":[["Fetching additional metadata from https://rubygems.org/..                                                            ",{}]]},"cursor":{"x":57}}],[0.000139,{"cursor":{"x":0,"y":4}}],[0.093164,{"lines":{"4":[["Resolving dependencies...                                                                                            ",{}]]},"cursor":{"x":25}}],[0.013643,{"cursor":{"x":0,"y":5}}],[0.009600000000000001,{"lines":{"5":[["Using rake 0.9.2.2                                                                                                   ",{}]],"6":[["Using parallel 1.0.0                                                                                                 ",{}]],"7":[["Using cane 2.6.2                                                                                                     ",{}]],"8":[["Using diff-lcs 1.2.5                                                                                                 ",{}]],"9":[["Using multi_json 1.10.1                                                                                              ",{}]],"10":[["Using redis 3.0.7                                                                                                    ",{}]]},"cursor":{"y":11}}],[0.113129,{"lines":{"11":[["Using qless 0.10.0.pre from git://github.com/seomoz/qless.git (at master)                                            ",{}]]},"cursor":{"y":12}}],[0.00067,{"lines":{"12":[["Using redis-objects 0.6.1                                                                                            ",{}]]},"cursor":{"y":13}}],[0.020792,{"lines":{"13":[["Using plines 0.5.1 from source at .                                                                                  ",{}]]},"cursor":{"y":14}}],[0.708031,{"lines":{"14":[["Installing rspec-support 3.1.2",{"fg":2}],["                                                                                       ",{}]]},"cursor":{"y":15}}],[1.21243,{"lines":{"15":[["Installing rspec-core 3.1.7 (was 2.99.2)",{"fg":2}],["                                                                             ",{}]]},"cursor":{"y":16}}],[0.445613,{"lines":{"0":[["➜ ",{"fg":1,"bold":true}],[" ",{"fg":2,"bold":true}],["plines ",{"fg":6,"bold":true}],["git:(",{"fg":4,"bold":true}],["rspec-3-upgrade",{"fg":1,"bold":true}],[") ",{"fg":4,"bold":true}],["✗",{"fg":3,"bold":true}],[" ",{"fg":4,"bold":true}],["bundle install                                                                     ",{}]],"1":[["Fetching gem metadata from https://rubygems.org/.......                                                              ",{}]],"2":[["Fetching additional metadata from https://rubygems.org/..                                                            ",{}]],"3":[["Resolving dependencies...                                                                                            ",{}]],"4":[["Using rake 0.9.2.2                                                                                                   ",{}]],"5":[["Using parallel 1.0.0                                                                                                 ",{}]],"6":[["Using cane 2.6.2                                                                                                     ",{}]],"7":[["Using diff-lcs 1.2.5                                                                                                 ",{}]],"8":[["Using multi_json 1.10.1                                                                                              ",{}]],"9":[["Using redis 3.0.7                                                                                                    ",{}]],"10":[["Using qless 0.10.0.pre from git://github.com/seomoz/qless.git (at master)                                            ",{}]],"11":[["Using redis-objects 0.6.1                                                                                            ",{}]],"12":[["Using plines 0.5.1 from source at .                                                                                  ",{}]],"13":[["Installing rspec-support 3.1.2",{"fg":2}],["                                                                                       ",{}]],"14":[["Installing rspec-core 3.1.7 (was 2.99.2)",{"fg":2}],["                                                                             ",{}]],"15":[["Installing rspec-expectations 3.1.2 (was 2.99.2)",{"fg":2}],["                                                                     ",{}]]}}],[0.878697,{"lines":{"0":[["Fetching gem metadata from https://rubygems.org/.......                                                              ",{}]],"1":[["Fetching additional metadata from https://rubygems.org/..                                                            ",{}]],"2":[["Resolving dependencies...                                                                                            ",{}]],"3":[["Using rake 0.9.2.2                                                                                                   ",{}]],"4":[["Using parallel 1.0.0                                                                                                 ",{}]],"5":[["Using cane 2.6.2                                                                                                     ",{}]],"6":[["Using diff-lcs 1.2.5                                                                                                 ",{}]],"7":[["Using multi_json 1.10.1                                                                                              ",{}]],"8":[["Using redis 3.0.7                                                                                                    ",{}]],"9":[["Using qless 0.10.0.pre from git://github.com/seomoz/qless.git (at master)                                            ",{}]],"10":[["Using redis-objects 0.6.1                                                                                            ",{}]],"11":[["Using plines 0.5.1 from source at .                                                                                  ",{}]],"12":[["Installing rspec-support 3.1.2",{"fg":2}],["                                                                                       ",{}]],"13":[["Installing rspec-core 3.1.7 (was 2.99.2)",{"fg":2}],["                                                                             ",{}]],"14":[["Installing rspec-expectations 3.1.2 (was 2.99.2)",{"fg":2}],["                                                                     ",{}]],"15":[["Installing rspec-mocks 3.1.3 (was 2.99.2)",{"fg":2}],["                                                                            ",{}]]}}],[0.677712,{"lines":{"0":[["Fetching additional metadata from https://rubygems.org/..                                                            ",{}]],"1":[["Resolving dependencies...                                                                                            ",{}]],"2":[["Using rake 0.9.2.2                                                                                                   ",{}]],"3":[["Using parallel 1.0.0                                                                                                 ",{}]],"4":[["Using cane 2.6.2                                                                                                     ",{}]],"5":[["Using diff-lcs 1.2.5                                                                                                 ",{}]],"6":[["Using multi_json 1.10.1                                                                                              ",{}]],"7":[["Using redis 3.0.7                                                                                                    ",{}]],"8":[["Using qless 0.10.0.pre from git://github.com/seomoz/qless.git (at master)                                            ",{}]],"9":[["Using redis-objects 0.6.1                                                                                            ",{}]],"10":[["Using plines 0.5.1 from source at .                                                                                  ",{}]],"11":[["Installing rspec-support 3.1.2",{"fg":2}],["                                                                                       ",{}]],"12":[["Installing rspec-core 3.1.7 (was 2.99.2)",{"fg":2}],["                                                                             ",{}]],"13":[["Installing rspec-expectations 3.1.2 (was 2.99.2)",{"fg":2}],["                                                                     ",{}]],"14":[["Installing rspec-mocks 3.1.3 (was 2.99.2)",{"fg":2}],["                                                                            ",{}]],"15":[["Installing rspec 3.1.0 (was 2.99.0)",{"fg":2}],["                                                                                  ",{}]]}}],[0.009844,{"lines":{"0":[["Using qless 0.10.0.pre from git://github.com/seomoz/qless.git (at master)                                            ",{}]],"1":[["Using redis-objects 0.6.1                                                                                            ",{}]],"2":[["Using plines 0.5.1 from source at .                                                                                  ",{}]],"3":[["Installing rspec-support 3.1.2",{"fg":2}],["                                                                                       ",{}]],"4":[["Installing rspec-core 3.1.7 (was 2.99.2)",{"fg":2}],["                                                                             ",{}]],"5":[["Installing rspec-expectations 3.1.2 (was 2.99.2)",{"fg":2}],["                                                                     ",{}]],"6":[["Installing rspec-mocks 3.1.3 (was 2.99.2)",{"fg":2}],["                                                                            ",{}]],"7":[["Installing rspec 3.1.0 (was 2.99.0)",{"fg":2}],["                                                                                  ",{}]],"8":[["Using simplecov-html 0.5.3                                                                                           ",{}]],"9":[["Using simplecov 0.6.4                                                                                                ",{}]],"10":[["Using timecop 0.3.5                                                                                                  ",{}]],"11":[["Using bundler 1.7.6                                                                                                  ",{}]],"12":[["Your bundle is complete!",{"fg":2}],["                                                                                             ",{}]],"13":[["It was installed into ./bundle",{"fg":2}],["                                                                                       ",{}]],"14":[["Removing rspec (2.99.0)                                                                                              ",{}]],"15":[["Removing rspec-core (2.99.2)                                                                                         ",{}]]}}],[0.015247,{"lines":{"0":[["Using redis-objects 0.6.1                                                                                            ",{}]],"1":[["Using plines 0.5.1 from source at .                                                                                  ",{}]],"2":[["Installing rspec-support 3.1.2",{"fg":2}],["                                                                                       ",{}]],"3":[["Installing rspec-core 3.1.7 (was 2.99.2)",{"fg":2}],["                                                                             ",{}]],"4":[["Installing rspec-expectations 3.1.2 (was 2.99.2)",{"fg":2}],["                                                                     ",{}]],"5":[["Installing rspec-mocks 3.1.3 (was 2.99.2)",{"fg":2}],["                                                                            ",{}]],"6":[["Installing rspec 3.1.0 (was 2.99.0)",{"fg":2}],["                                                                                  ",{}]],"7":[["Using simplecov-html 0.5.3                                                                                           ",{}]],"8":[["Using simplecov 0.6.4                                                                                                ",{}]],"9":[["Using timecop 0.3.5                                                                                                  ",{}]],"10":[["Using bundler 1.7.6                                                                                                  ",{}]],"11":[["Your bundle is complete!",{"fg":2}],["                                                                                             ",{}]],"12":[["It was installed into ./bundle",{"fg":2}],["                                                                                       ",{}]],"13":[["Removing rspec (2.99.0)                                                                                              ",{}]],"14":[["Removing rspec-core (2.99.2)                                                                                         ",{}]],"15":[["Removing rspec-expectations (2.99.2)                                                                                 ",{}]]}}],[0.012805,{"lines":{"0":[["Using plines 0.5.1 from source at .                                                                                  ",{}]],"1":[["Installing rspec-support 3.1.2",{"fg":2}],["                                                                                       ",{}]],"2":[["Installing rspec-core 3.1.7 (was 2.99.2)",{"fg":2}],["                                                                             ",{}]],"3":[["Installing rspec-expectations 3.1.2 (was 2.99.2)",{"fg":2}],["                                                                     ",{}]],"4":[["Installing rspec-mocks 3.1.3 (was 2.99.2)",{"fg":2}],["                                                                            ",{}]],"5":[["Installing rspec 3.1.0 (was 2.99.0)",{"fg":2}],["                                                                                  ",{}]],"6":[["Using simplecov-html 0.5.3                                                                                           ",{}]],"7":[["Using simplecov 0.6.4                                                                                                ",{}]],"8":[["Using timecop 0.3.5                                                                                                  ",{}]],"9":[["Using bundler 1.7.6                                                                                                  ",{}]],"10":[["Your bundle is complete!",{"fg":2}],["                                                                                             ",{}]],"11":[["It was installed into ./bundle",{"fg":2}],["                                                                                       ",{}]],"12":[["Removing rspec (2.99.0)                                                                                              ",{}]],"13":[["Removing rspec-core (2.99.2)                                                                                         ",{}]],"14":[["Removing rspec-expectations (2.99.2)                                                                                 ",{}]],"15":[["Removing rspec-mocks (2.99.2)                                                                                        ",{}]]}}],[0.10727,{}],[8.7e-05,{}],[0.016694,{"lines":{"16":[["➜ ",{"fg":1,"bold":true}],[" ",{"fg":2,"bold":true}],["plines ",{"fg":6,"bold":true}],["git:(",{"fg":4,"bold":true}],["rspec-3-upgrade",{"fg":1,"bold":true}],[") ",{"fg":4,"bold":true}],["✗",{"fg":3,"bold":true}],[" ",{"fg":4,"bold":true}],["                                                                                   ",{}]]},"cursor":{"x":34}}],[1.064505,{"lines":{"0":[["Installing rspec-support 3.1.2",{"fg":2}],["                                                                                       ",{}]],"1":[["Installing rspec-core 3.1.7 (was 2.99.2)",{"fg":2}],["                                                                             ",{}]],"2":[["Installing rspec-expectations 3.1.2 (was 2.99.2)",{"fg":2}],["                                                                     ",{}]],"3":[["Installing rspec-mocks 3.1.3 (was 2.99.2)",{"fg":2}],["                                                                            ",{}]],"4":[["Installing rspec 3.1.0 (was 2.99.0)",{"fg":2}],["                                                                                  ",{}]],"5":[["Using simplecov-html 0.5.3                                                                                           ",{}]],"6":[["Using simplecov 0.6.4                                                                                                ",{}]],"7":[["Using timecop 0.3.5                                                                                                  ",{}]],"8":[["Using bundler 1.7.6                                                                                                  ",{}]],"9":[["Your bundle is complete!",{"fg":2}],["                                                                                             ",{}]],"10":[["It was installed into ./bundle",{"fg":2}],["                                                                                       ",{}]],"11":[["Removing rspec (2.99.0)                                                                                              ",{}]],"12":[["Removing rspec-core (2.99.2)                                                                                         ",{}]],"13":[["Removing rspec-expectations (2.99.2)                                                                                 ",{}]],"14":[["Removing rspec-mocks (2.99.2)                                                                                        ",{}]],"15":[["➜ ",{"fg":1,"bold":true}],[" ",{"fg":2,"bold":true}],["plines ",{"fg":6,"bold":true}],["git:(",{"fg":4,"bold":true}],["rspec-3-upgrade",{"fg":1,"bold":true}],[") ",{"fg":4,"bold":true}],["✗",{"fg":3,"bold":true}],[" ",{"fg":4,"bold":true}],["                                                                                   ",{}]],"16":[["                                                                                                                     ",{}]]},"cursor":{"x":0}}]]