[[0.05236,{"lines":{"0":[["vaibhavg@ubuntu:~$                                                              ",{}]],"1":[["                                                                                ",{}]],"2":[["                                                                                ",{}]],"3":[["                                                                                ",{}]],"4":[["                                                                                ",{}]],"5":[["                                                                                ",{}]],"6":[["                                                                                ",{}]],"7":[["                                                                                ",{}]],"8":[["                                                                                ",{}]],"9":[["                                                                                ",{}]],"10":[["                                                                                ",{}]],"11":[["                                                                                ",{}]],"12":[["                                                                                ",{}]],"13":[["                                                                                ",{}]],"14":[["                                                                                ",{}]],"15":[["                                                                                ",{}]],"16":[["                                                                                ",{}]],"17":[["                                                                                ",{}]],"18":[["                                                                                ",{}]],"19":[["                                                                                ",{}]],"20":[["                                                                                ",{}]],"21":[["                                                                                ",{}]],"22":[["                                                                                ",{}]],"23":[["                                                                                ",{}]]},"cursor":{"x":19,"y":0,"visible":true}}],[1.653436,{"lines":{"0":[["vaibhavg@ubuntu:~$ d                                                            ",{}]]},"cursor":{"x":20}}],[0.159683,{"lines":{"0":[["vaibhavg@ubuntu:~$ da                                                           ",{}]]},"cursor":{"x":21}}],[0.248562,{"lines":{"0":[["vaibhavg@ubuntu:~$ dat                                                          ",{}]]},"cursor":{"x":22}}],[0.104013,{"lines":{"0":[["vaibhavg@ubuntu:~$ date                                                         ",{}]]},"cursor":{"x":23}}],[0.401784,{"lines":{"1":[["Sun Nov 23 09:23:07 PST 2014                                                    ",{}]]},"cursor":{"x":0,"y":2}}],[0.000217,{"lines":{"2":[["vaibhavg@ubuntu:~$                                                              ",{}]]},"cursor":{"x":19}}],[1.085742,{"lines":{"2":[["vaibhavg@ubuntu:~$ e                                                            ",{}]]},"cursor":{"x":20}}],[0.303925,{"lines":{"2":[["vaibhavg@ubuntu:~$ ec                                                           ",{}]]},"cursor":{"x":21}}],[0.223685,{"lines":{"2":[["vaibhavg@ubuntu:~$ ech                                                          ",{}]]},"cursor":{"x":22}}],[0.216218,{"lines":{"2":[["vaibhavg@ubuntu:~$ echo                                                         ",{}]]},"cursor":{"x":23}}],[0.105121,{"cursor":{"x":24}}],[0.286676,{"lines":{"2":[["vaibhavg@ubuntu:~$ echo h                                                       ",{}]]},"cursor":{"x":25}}],[0.207494,{"lines":{"2":[["vaibhavg@ubuntu:~$ echo he                                                      ",{}]]},"cursor":{"x":26}}],[0.248361,{"lines":{"2":[["vaibhavg@ubuntu:~$ echo hel                                                     ",{}]]},"cursor":{"x":27}}],[0.191362,{"lines":{"2":[["vaibhavg@ubuntu:~$ echo hell                                                    ",{}]]},"cursor":{"x":28}}],[0.176761,{"lines":{"2":[["vaibhavg@ubuntu:~$ echo hello                                                   ",{}]]},"cursor":{"x":29}}],[0.208329,{"lines":{"3":[["hello                                                                           ",{}]],"4":[["vaibhavg@ubuntu:~$                                                              ",{}]]},"cursor":{"x":19,"y":4}}],[0.902939,{"lines":{"4":[["vaibhavg@ubuntu:~$ e                                                            ",{}]]},"cursor":{"x":20}}],[0.255597,{"lines":{"4":[["vaibhavg@ubuntu:~$ ex                                                           ",{}]]},"cursor":{"x":21}}],[0.32103,{"lines":{"4":[["vaibhavg@ubuntu:~$ exi                                                          ",{}]]},"cursor":{"x":22}}],[0.127845,{"lines":{"4":[["vaibhavg@ubuntu:~$ exit                                                         ",{}]]},"cursor":{"x":23}}],[0.12085,{"lines":{"5":[["exit                                                                            ",{}]]},"cursor":{"x":0,"y":6}}]]